leap.pixelated_www-1.0.201709121424-py2.7-nspkg.pth
leap/pixelated_www/__init__.py
leap/pixelated_www/protected/2.2.js
leap/pixelated_www/protected/2.2.js.map
leap/pixelated_www/protected/404.html
leap/pixelated_www/protected/674f50d287a8c48dc19ba404d20fe713.eot
leap/pixelated_www/protected/912ec66d7572ff821749319396470bde.svg
leap/pixelated_www/protected/account_recovery.html
leap/pixelated_www/protected/af7ae505a9eed503f8b8e6982036873e.woff2
leap/pixelated_www/protected/app.js
leap/pixelated_www/protected/app.js.map
leap/pixelated_www/protected/b06871f281fee6b241d60582ae9369b9.ttf
leap/pixelated_www/protected/backup_account.html
leap/pixelated_www/protected/backup_account.js
leap/pixelated_www/protected/backup_account.js.map
leap/pixelated_www/protected/fee66e712a8a08eef5805a46892932ad.woff
leap/pixelated_www/protected/foundation.js
leap/pixelated_www/protected/foundation.offcanvas.js
leap/pixelated_www/protected/foundation.reveal.js
leap/pixelated_www/protected/handlebars.min.js
leap/pixelated_www/protected/iframeResizer.contentWindow.min.js
leap/pixelated_www/protected/iframeResizer.min.js
leap/pixelated_www/protected/index.html
leap/pixelated_www/protected/initialize_foundation.js
leap/pixelated_www/protected/jquery-ui.min.js
leap/pixelated_www/protected/jquery.fileupload.js
leap/pixelated_www/protected/jquery.min.js
leap/pixelated_www/protected/lodash.min.js
leap/pixelated_www/protected/modernizr.js
leap/pixelated_www/protected/sandbox.html
leap/pixelated_www/protected/sandbox.js
leap/pixelated_www/protected/sandbox.js.map
leap/pixelated_www/protected/typeahead.bundle.min.js
leap/pixelated_www/protected/css/font-awesome.min.css
leap/pixelated_www/protected/css/jquery.fileupload.css
leap/pixelated_www/protected/css/sandbox.css
leap/pixelated_www/protected/css/style.css
leap/pixelated_www/protected/fonts/FontAwesome.otf
leap/pixelated_www/protected/fonts/fontawesome-webfont.eot
leap.pixelated_www-1.0.201709121424.dist-info/DESCRIPTION.rst
leap.pixelated_www-1.0.201709121424.dist-info/METADATA
leap.pixelated_www-1.0.201709121424.dist-info/RECORD
leap.pixelated_www-1.0.201709121424.dist-info/WHEEL
leap.pixelated_www-1.0.201709121424.dist-info/metadata.json
leap.pixelated_www-1.0.201709121424.dist-info/namespace_packages.txt
leap.pixelated_www-1.0.201709121424.dist-info/top_level.txt
