Metadata-Version: 2.0
Name: leap.pixelated-www
Version: 1.0.201709121424
Summary: Static Assets for the Pixelated User Agent UI
Home-page: http://github.com/leapcode/pixelated-user-agent
Author: LEAP Encryption Access Project
Author-email: info@leap.se
License: GNU Affero General Public License v3 or later (AGPLv3+)
Platform: UNKNOWN
